easypymanager/__init__.py
easypymanager/easypymanager.py
easypymanager-1.2.1.dist-info/LICENSE
easypymanager-1.2.1.dist-info/METADATA
easypymanager-1.2.1.dist-info/WHEEL
easypymanager-1.2.1.dist-info/entry_points.txt
easypymanager-1.2.1.dist-info/top_level.txt
easypymanager-1.2.1.dist-info/RECORD
