Metadata-Version: 2.1
Name: easypymanager
Version: 1.2.1
Summary: EasyPyManager is a GUI application for managing and executing Python scripts. 
Author: sysucai
Author-email: 411703730@qq.com
Platform: Any platform -- don't need Windows
Classifier: Programming Language :: Python :: 3
Classifier: License :: OSI Approved :: MIT License
Classifier: Operating System :: OS Independent
Requires-Python: >=3.7
License-File: LICENSE
